lesson7_synthesis/full_adder.v
module full_adder (
    input a,
    input b,
    input cin,
    output sum,
    output cout
);
    assign sum = a ^ b ^ cin;
    assign cout = (a & b) | (cin & (a ^ b));
endmodule

lesson5_combinational/full_adder_tb.v
`timescale 1ns/1ps
module full_adder_tb;
    reg a, b, cin;
    wire sum, cout;

    full_adder uut (.a(a), .b(b), .cin(cin), .sum(sum), .cout(cout));

    initial begin
        $dumpfile("full_adder.vcd");
        $dumpvars(0, full_adder_tb);

        a=0; b=0; cin=0; #10; // 0+0+0 = sum 0, cout 0
        a=0; b=1; cin=0; #10; // 0+1+0 = sum 1, cout 0
        a=1; b=0; cin=0; #10; // 1+0+0 = sum 1, cout 0
        a=1; b=1; cin=0; #10; // 1+1+0 = sum 0, cout 1
        a=0; b=0; cin=1; #10; // 0+0+1 = sum 1, cout 0
        a=0; b=1; cin=1; #10; // 0+1+1 = sum 0, cout 1
        a=1; b=0; cin=1; #10; // 1+0+1 = sum 0, cout 1
        a=1; b=1; cin=1; #10; // 1+1+1 = sum 1, cout 1

        $finish;
    end
endmodule

lesson5_combinational/full_adder.vcd
$date
	Mon Sep 21 15:13:30 2026
$end
$version
	Icarus Verilog
$end
$timescale
	1ps
$end
$scope module full_adder_tb $end
$var wire 1 ! sum $end
$var wire 1 " cout $end
$var reg 1 # a $end
$var reg 1 $ b $end
$var reg 1 % cin $end
$scope module uut $end
$var wire 1 # a $end
$var wire 1 $ b $end
$var wire 1 % cin $end
$var wire 1 " cout $end
$var wire 1 ! sum $end
$upscope $end
$upscope $end
$enddefinitions $end
$comment Show the parameter values. $end
$dumpall
$end
#0
$dumpvars
0%
0$
0#
0"
0!
$end
#10000
1!
1$
#20000
0$
1#
#30000
0!
1"
1$
#40000
0"
1!
1%
0$
0#
#50000
1"
0!
1$
#60000
0$
1#
#70000
1!
1$
