lesson6_sequential/fsm_traffic_light.v
module fsm_traffic_light (
    input clk,
    input rst,
    output reg [1:0] light // 00=Red, 01=Yellow, 10=Green
);

    // State encoding using localparam for better readability
    localparam RED    = 2'b00;
    localparam YELLOW = 2'b01;
    localparam GREEN  = 2'b10;

    // Internal state registers
    reg [1:0] current_state, next_state;

    // 1. State Register (Sequential Logic)
    // Updates state ONLY on the rising edge of the clock
    always @(posedge clk or posedge rst) begin
        if (rst) begin
            current_state <= RED;
        end else begin
            current_state <= next_state;
        end
    end

    // 2. Next State Logic (Combinational Logic)
    // Determines what the next state should be based on current state
    always @(*) begin
        case (current_state)
            RED:    next_state = GREEN;
            GREEN:  next_state = YELLOW;
            YELLOW: next_state = RED;
            default: next_state = RED;
        endcase
    end

    // 3. Output Logic (Combinational Logic)
    // Maps the current state to the output light
    always @(*) begin
        case (current_state)
            RED:    light = 2'b00;
            YELLOW: light = 2'b01;
            GREEN:  light = 2'b10;
            default: light = 2'b00;
        endcase
    end

endmodule

lesson6_sequential/fsm_traffic_light_tb.v
`timescale 1ns/1ps
module fsm_traffic_light_tb;
    reg clk;
    reg rst;
    wire [1:0] light;

    // Instantiate the FSM
    fsm_traffic_light uut (
        .clk(clk),
        .rst(rst),
        .light(light)
    );

    // Clock generation: 10ns period
    initial begin
        clk = 0;
        forever #5 clk = ~clk; 
    end

    initial begin
        $dumpfile("fsm_traffic_light.vcd");
        $dumpvars(0, fsm_traffic_light_tb);

        // Apply reset
        rst = 1;
        #10;
        rst = 0; // Release reset

        // Let it run for 100ns to see the lights change
        #100;
        
        $finish;
    end
endmodule

lesson6_sequential/fsm_traffic_light.vcd
$date
	Mon Sep 21 17:58:00 2026
$end
$version
	Icarus Verilog
$end
$timescale
	1ps
$end
$scope module fsm_traffic_light_tb $end
$var wire 2 ! light [1:0] $end
$var reg 1 " clk $end
$var reg 1 # rst $end
$scope module uut $end
$var wire 1 " clk $end
$var wire 1 # rst $end
$var parameter 2 $ GREEN $end
$var parameter 2 % RED $end
$var parameter 2 & YELLOW $end
$var reg 2 ' current_state [1:0] $end
$var reg 2 ( light [1:0] $end
$var reg 2 ) next_state [1:0] $end
$upscope $end
$upscope $end
$enddefinitions $end
$comment Show the parameter values. $end
$dumpall
b1 &
b0 %
b10 $
$end
#0
$dumpvars
b10 )
b0 (
b0 '
1#
0"
b0 !
$end
#5000
1"
#10000
0"
0#
#15000
b1 )
b10 !
b10 (
b10 '
1"
#20000
0"
#25000
b1 !
b1 (
b0 )
b1 '
1"
#30000
0"
#35000
b10 )
b0 !
b0 (
b0 '
1"
#40000
0"
#45000
b10 !
b10 (
b1 )
b10 '
1"
#50000
0"
#55000
b0 )
b1 !
b1 (
b1 '
1"
#60000
0"
#65000
b0 !
b0 (
b10 )
b0 '
1"
#70000
0"
#75000
b1 )
b10 !
b10 (
b10 '
1"
#80000
0"
#85000
b1 !
b1 (
b0 )
b1 '
1"
#90000
0"
#95000
b10 )
b0 !
b0 (
b0 '
1"
#100000
0"
#105000
b10 !
b10 (
b1 )
b10 '
1"
